{
    "leadership": [
        {
            "name": "Gabby Jackson",
            "position": "Teaching Committee Head",
            "email": "gej3@rice.edu",
            "year": "2020",
            "picture": "/static/gej3.png"
        },
        {
            "name": "Patrick Brady",
            "position": "Teaching Committee Head",
            "email": "pjb3@rice.edu",
            "year": "2020",
            "picture": "/static/pjb3.png"
        },
        {
            "name": "Grace Tan",
            "position": "Community Engagement Head",
            "email": "gzt1@rice.edu",
            "year": "2021",
            "picture": "/static/gzt1.png"
        },
        {
            "name": "Valerie Hellmer",
            "position": "Community Engagement Head",
            "email": "vah3@rice.edu",
            "year": "2021",
            "picture": "/static/vah3.png"
        },
        {
            "name": "Samra Belachew",
            "position": "Curriculum Committee Head",
            "email": "sdb13@rice.edu",
            "year": "2020",
            "picture": "/static/sdb13.png"
        },
        {
            "name": "Nicholas Meisburger",
            "position": "Curriculum Committee Head",
            "email": "ncm5@rice.edu",
            "year": "2022",
            "picture": "/static/ncm5.jpg"
        },
        {
            "name": "Raul Palomo",
            "position": "Teaching Committee & Curriculum Committee Liaison",
            "email": "rrp10@rice.edu",
            "year": "2020",
            "picture": "/static/rrp10.JPG"
        },
        {
            "name": "Prashanth Pai",
            "position": "Community Engagement",
            "email": "pbp2@rice.edu",
            "year": "2022",
            "picture": "/static/pbp2.png"
        }
    ]
}